DotDotDeee/DotDotDee.py
DotDotDeee/__init__.py
tests/__init__.py
tests/test_dotdotdee.py
DotDotDeee-1.1.0.dist-info/METADATA
DotDotDeee-1.1.0.dist-info/WHEEL
DotDotDeee-1.1.0.dist-info/top_level.txt
DotDotDeee-1.1.0.dist-info/RECORD
