Metadata-Version: 2.1
Name: DotDotDeee
Version: 1.1.0
Summary: A Python library that solves the ModuleNotFoundError: No module named <folder_name> issue
Author: @pollitoconpapass
